dtor/__init__.py
dtor/tor_lib.py
dtor-0.1.0.dist-info/licenses/LICENSE
dtor-0.1.0.dist-info/METADATA
dtor-0.1.0.dist-info/WHEEL
dtor-0.1.0.dist-info/top_level.txt
dtor-0.1.0.dist-info/RECORD
