Metadata-Version: 2.4
Name: dtor
Version: 0.1.0
Summary: A Tor process management library
Home-page: https://github.com/QudsLab/dtor
Author: Ahmad Yousuf
Author-email: 0xAhmadYousuf@protonmail.com
License: MIT
Project-URL: Bug Reports, https://github.com/QudsLab/dtor/issues
Project-URL: Source, https://github.com/QudsLab/dtor
Keywords: tor,proxy,anonymity,privacy,hidden-service,onion
Classifier: Development Status :: 4 - Beta
Classifier: Intended Audience :: Developers
Classifier: License :: OSI Approved :: MIT License
Classifier: Programming Language :: Python :: 3
Classifier: Programming Language :: Python :: 3.8
Classifier: Programming Language :: Python :: 3.9
Classifier: Programming Language :: Python :: 3.10
Classifier: Programming Language :: Python :: 3.11
Classifier: Programming Language :: Python :: 3.12
Classifier: Operating System :: OS Independent
Classifier: Topic :: Software Development :: Libraries :: Python Modules
Classifier: Topic :: Internet :: Proxy Servers
Classifier: Topic :: Security
Requires-Python: >=3.8
License-File: LICENSE
Requires-Dist: psutil>=5.9.0
Requires-Dist: requests>=2.28.0
Requires-Dist: setuptools>=65.0.0
Requires-Dist: wheel>=0.38.0
Dynamic: author
Dynamic: author-email
Dynamic: classifier
Dynamic: description
Dynamic: description-content-type
Dynamic: home-page
Dynamic: keywords
Dynamic: license
Dynamic: license-file
Dynamic: project-url
Dynamic: requires-dist
Dynamic: requires-python
Dynamic: summary
